MANIFEST.in
README.rst
requirements.txt
setup.cfg
setup.py
kotti_migration/__init__.py
kotti_migration/__init__.pyc
kotti_migration/config.py
kotti_migration/config.pyc
kotti_migration/fanstatic.py
kotti_migration/fanstatic.pyc
kotti_migration/resources.py
kotti_migration/resources.pyc
kotti_migration/util.py
kotti_migration/util.pyc
kotti_migration.egg-info/PKG-INFO
kotti_migration.egg-info/SOURCES.txt
kotti_migration.egg-info/dependency_links.txt
kotti_migration.egg-info/entry_points.txt
kotti_migration.egg-info/not-zip-safe
kotti_migration.egg-info/requires.txt
kotti_migration.egg-info/top_level.txt
kotti_migration/scripts/__init__.py
kotti_migration/scripts/__init__.pyc
kotti_migration/scripts/migrator.py
kotti_migration/scripts/migrator.pyc
kotti_migration/static/scripts.js
kotti_migration/static/scripts.min.js
kotti_migration/static/styles.css
kotti_migration/static/styles.min.css
kotti_migration/templates/import.pt
kotti_migration/tests/conftest.py
kotti_migration/tests/test_functional.py
kotti_migration/tests/test_resources.py
kotti_migration/tests/test_view.py
kotti_migration/views/__init__.py
kotti_migration/views/__init__.pyc
kotti_migration/views/edit.py
kotti_migration/views/edit.pyc
kotti_migration/views/view.pyc